odoo/addons/product_abc_classification/README.rst
odoo/addons/product_abc_classification/__init__.py
odoo/addons/product_abc_classification/__manifest__.py
odoo/addons/product_abc_classification/data/ir_cron.xml
odoo/addons/product_abc_classification/i18n/product_abc_classification.pot
odoo/addons/product_abc_classification/models/__init__.py
odoo/addons/product_abc_classification/models/abc_classification_level.py
odoo/addons/product_abc_classification/models/abc_classification_profile.py
odoo/addons/product_abc_classification/models/product_category.py
odoo/addons/product_abc_classification/models/product_product.py
odoo/addons/product_abc_classification/readme/CONTRIBUTORS.rst
odoo/addons/product_abc_classification/readme/DESCRIPTION.rst
odoo/addons/product_abc_classification/readme/USAGE.rst
odoo/addons/product_abc_classification/security/ir.model.access.csv
odoo/addons/product_abc_classification/static/description/icon.png
odoo/addons/product_abc_classification/static/description/index.html
odoo/addons/product_abc_classification/views/abc_classification_view.xml
odoo/addons/product_abc_classification/views/product_view.xml
odoo13_addon_product_abc_classification-13.0.3.0.0.dist-info/METADATA
odoo13_addon_product_abc_classification-13.0.3.0.0.dist-info/WHEEL
odoo13_addon_product_abc_classification-13.0.3.0.0.dist-info/top_level.txt
odoo13_addon_product_abc_classification-13.0.3.0.0.dist-info/RECORD
